mlreserving/__init__.py
mlreserving/ml_reserving.py
mlreserving/utils.py
mlreserving-0.3.0.dist-info/licenses/LICENSE
mlreserving-0.3.0.dist-info/METADATA
mlreserving-0.3.0.dist-info/WHEEL
mlreserving-0.3.0.dist-info/top_level.txt
mlreserving-0.3.0.dist-info/RECORD
