Metadata-Version: 2.4
Name: mlreserving
Version: 0.3.0
Summary: Model-agnostic Probabilistic Machine Learning Reserving
Home-page: https://github.com/Techtonique/mlreserving
Author: T. Moudiki
Author-email: "T. Moudiki" <thierry.moudiki@gmail.com>
Project-URL: Repository, https://github.com/Techtonique/mlreserving
Classifier: Programming Language :: Python :: 3
Classifier: License :: OSI Approved :: BSD License
Classifier: Operating System :: OS Independent
Requires-Python: >=3.7
License-File: LICENSE
Requires-Dist: nnetsauce>=0.17.0
Requires-Dist: numpy>=1.20.0
Requires-Dist: pandas>=1.3.0
Requires-Dist: scikit-learn>=1.0.0
Requires-Dist: joblib>=1.1.0
Dynamic: author
Dynamic: home-page
Dynamic: license-file
Dynamic: requires-python
